{
  "base": "EUR",
  "currencies": [
    {
      "code": "EUR",
      "name": "Euro",
      "rate_to_eur": 1.0,
      "correction_to_eur": 0.0,
      "source": "fixed",
      "updated_at": "2026-06-16T15:23:34+00:00",
      "active": true
    },
    {
      "code": "USD",
      "name": "US Dollar",
      "rate_to_eur": 0.8619203585588693,
      "correction_to_eur": 0.0,
      "source": "Frankfurter",
      "updated_at": "2026-06-16T15:23:34+00:00",
      "active": true
    },
    {
      "code": "GBP",
      "name": "British Pound",
      "rate_to_eur": 1.1569521253210542,
      "correction_to_eur": 0.0,
      "source": "Frankfurter",
      "updated_at": "2026-06-16T15:23:34+00:00",
      "active": true
    },
    {
      "code": "CHF",
      "name": "Swiss Franc",
      "rate_to_eur": 1.0849517196484757,
      "correction_to_eur": 0.0,
      "source": "Frankfurter",
      "updated_at": "2026-06-16T15:23:34+00:00",
      "active": true
    },
    {
      "code": "SEK",
      "name": "Swedish Krona",
      "rate_to_eur": 0.0917397526696268,
      "correction_to_eur": 0.0,
      "source": "Frankfurter",
      "updated_at": "2026-06-16T15:23:34+00:00",
      "active": true
    },
    {
      "code": "NOK",
      "name": "Norwegian Krone",
      "rate_to_eur": 0.09046662686135085,
      "correction_to_eur": 0.0,
      "source": "Frankfurter",
      "updated_at": "2026-06-16T15:23:34+00:00",
      "active": true
    },
    {
      "code": "DKK",
      "name": "Danish Krone",
      "rate_to_eur": 0.13372738335628986,
      "correction_to_eur": 0.0,
      "source": "Frankfurter",
      "updated_at": "2026-06-16T15:23:34+00:00",
      "active": true
    },
    {
      "code": "CAD",
      "name": "Canadian Dollar",
      "rate_to_eur": 0.6158014656074882,
      "correction_to_eur": 0.0,
      "source": "Frankfurter",
      "updated_at": "2026-06-16T15:23:34+00:00",
      "active": true
    },
    {
      "code": "AUD",
      "name": "Australian Dollar",
      "rate_to_eur": 0.6086797735711242,
      "correction_to_eur": 0.0,
      "source": "Frankfurter",
      "updated_at": "2026-06-16T15:23:34+00:00",
      "active": true
    },
    {
      "code": "JPY",
      "name": "Japanese Yen",
      "rate_to_eur": 0.0053751881315846056,
      "correction_to_eur": 0.0,
      "source": "Frankfurter",
      "updated_at": "2026-06-16T15:23:34+00:00",
      "active": true
    }
  ],
  "last_refresh_attempt": "2026-06-16T15:23:34+00:00",
  "last_successful_refresh": "2026-06-16T15:23:34+00:00",
  "last_error": ""
}